setup.py
distributions/Binomialdistribution.py
distributions/Gaussiandistribution.py
distributions/Generaldistribution.py
distributions/__init__.py
taonga.egg-info/PKG-INFO
taonga.egg-info/SOURCES.txt
taonga.egg-info/dependency_links.txt
taonga.egg-info/not-zip-safe
taonga.egg-info/top_level.txt